{
    "fluentMethods": true,
    "relationships": [],
    "fields": [
        {
            "fieldName": "idModulo",
            "fieldType": "Integer",
            "fieldValidateRules": [
                "required"
            ]
        },
        {
            "fieldName": "nombre",
            "fieldType": "String",
            "fieldValidateRules": [
                "required"
            ]
        },
        {
            "fieldName": "estatus",
            "fieldType": "Boolean"
        },
        {
            "fieldName": "fechaCreacion",
            "fieldType": "LocalDate"
        },
        {
            "fieldName": "fechaModificacion",
            "fieldType": "LocalDate"
        }
    ],
    "changelogDate": "20180510172445",
    "entityTableName": "modulo",
    "dto": "no",
    "pagination": "pagination",
    "service": "no",
    "jpaMetamodelFiltering": false
}